README.md
setup.py
libpythonjarlan.egg-info/PKG-INFO
libpythonjarlan.egg-info/SOURCES.txt
libpythonjarlan.egg-info/dependency_links.txt
libpythonjarlan.egg-info/not-zip-safe
libpythonjarlan.egg-info/requires.txt
libpythonjarlan.egg-info/top_level.txt
libpythonpro/__init__.py
libpythonpro/github_api.py